kp_registry/__init__.py
kp_registry/main.py
kp_registry-4.0.1.dist-info/METADATA
kp_registry-4.0.1.dist-info/WHEEL
kp_registry-4.0.1.dist-info/top_level.txt
kp_registry-4.0.1.dist-info/RECORD
