Metadata-Version: 2.1
Name: kp-registry
Version: 4.0.1
Summary: Translator KP Registry
Home-page: https://github.com/ranking-agent/kp_registry
Author: CoVar
License: MIT
Platform: UNKNOWN
Requires-Python: >=3.6
Requires-Dist: httpx
Requires-Dist: reasoner-pydantic
